{
	"info": {
		"_postman_id": "3d5e8eea-0ba5-4d1c-864f-4ffeb0b4e535",
		"name": "penny",
		"schema": "https://schema.getpostman.com/json/collection/v2.1.0/collection.json",
		"_exporter_id": "26407390"
	},
	"item": [
		{
			"name": "User",
			"item": [
				{
					"name": "Register",
					"item": [
						{
							"name": "Error",
							"item": [
								{
									"name": "testUsername",
									"request": {
										"auth": {
											"type": "bearer"
										},
										"method": "POST",
										"header": [],
										"body": {
											"mode": "urlencoded",
											"urlencoded": [
												{
													"key": "username",
													"value": "bragalotwill",
													"type": "text"
												},
												{
													"key": "password",
													"value": "pass123",
													"type": "text"
												},
												{
													"key": "displayName",
													"value": "wila braga",
													"type": "text"
												},
												{
													"key": "email",
													"value": "braga1@gmail.com",
													"type": "text"
												}
											]
										},
										"url": {
											"raw": "http://localhost:5000/api/users/register",
											"protocol": "http",
											"host": [
												"localhost"
											],
											"port": "5000",
											"path": [
												"api",
												"users",
												"register"
											],
											"query": [
												{
													"key": "username",
													"value": "bragalotwill",
													"disabled": true
												}
											]
										}
									},
									"response": [
										{
											"name": "testUsernameExists",
											"originalRequest": {
												"method": "POST",
												"header": [],
												"body": {
													"mode": "urlencoded",
													"urlencoded": [
														{
															"key": "username",
															"value": "bragalotwill",
															"type": "text"
														},
														{
															"key": "password",
															"value": "pass123",
															"type": "text"
														},
														{
															"key": "displayName",
															"value": "wila braga",
															"type": "text"
														},
														{
															"key": "email",
															"value": "braga@gmail.com",
															"type": "text"
														}
													]
												},
												"url": {
													"raw": "http://localhost:5000/api/users/register",
													"protocol": "http",
													"host": [
														"localhost"
													],
													"port": "5000",
													"path": [
														"api",
														"users",
														"register"
													],
													"query": [
														{
															"key": "username",
															"value": "bragalotwill",
															"disabled": true
														}
													]
												}
											},
											"_postman_previewlanguage": null,
											"header": null,
											"cookie": [],
											"body": null
										},
										{
											"name": "testUsernameTooSmall",
											"originalRequest": {
												"method": "POST",
												"header": [],
												"body": {
													"mode": "urlencoded",
													"urlencoded": [
														{
															"key": "username",
															"value": "brag",
															"type": "text"
														},
														{
															"key": "password",
															"value": "pass123",
															"type": "text"
														},
														{
															"key": "displayName",
															"value": "wila braga",
															"type": "text"
														},
														{
															"key": "email",
															"value": "braga2@gmail.com",
															"type": "text"
														}
													]
												},
												"url": {
													"raw": "http://localhost:5000/api/users/register",
													"protocol": "http",
													"host": [
														"localhost"
													],
													"port": "5000",
													"path": [
														"api",
														"users",
														"register"
													],
													"query": [
														{
															"key": "username",
															"value": "bragalotwill",
															"disabled": true
														}
													]
												}
											},
											"_postman_previewlanguage": null,
											"header": null,
											"cookie": [],
											"body": null
										},
										{
											"name": "testNoUsername",
											"originalRequest": {
												"method": "POST",
												"header": [
													{
														"key": "Content-Type",
														"name": "Content-Type",
														"value": "application/x-www-form-urlencoded",
														"type": "text"
													}
												],
												"body": {
													"mode": "urlencoded",
													"urlencoded": [
														{
															"key": "username",
															"value": "",
															"type": "text",
															"disabled": true
														},
														{
															"key": "password",
															"value": "pass123",
															"type": "text"
														},
														{
															"key": "displayName",
															"value": "wila braga1",
															"type": "text"
														},
														{
															"key": "email",
															"value": "braga1@gmail.com",
															"type": "text"
														}
													]
												},
												"url": {
													"raw": "http://localhost:5000/api/users/register",
													"protocol": "http",
													"host": [
														"localhost"
													],
													"port": "5000",
													"path": [
														"api",
														"users",
														"register"
													]
												}
											},
											"_postman_previewlanguage": null,
											"header": null,
											"cookie": [],
											"body": null
										},
										{
											"name": "testUsernameTooBig",
											"originalRequest": {
												"method": "POST",
												"header": [],
												"body": {
													"mode": "urlencoded",
													"urlencoded": [
														{
															"key": "username",
															"value": "bragalotwilltjeosmvi",
															"type": "text"
														},
														{
															"key": "password",
															"value": "pass123",
															"type": "text"
														},
														{
															"key": "displayName",
															"value": "wila braga1",
															"type": "text"
														},
														{
															"key": "email",
															"value": "braga1@gmail.com",
															"type": "text"
														}
													]
												},
												"url": {
													"raw": "http://localhost:5000/api/users/register",
													"protocol": "http",
													"host": [
														"localhost"
													],
													"port": "5000",
													"path": [
														"api",
														"users",
														"register"
													],
													"query": [
														{
															"key": "username",
															"value": "bragalotwill",
															"disabled": true
														}
													]
												}
											},
											"_postman_previewlanguage": null,
											"header": null,
											"cookie": [],
											"body": null
										},
										{
											"name": "testUsernameInvalidChars",
											"originalRequest": {
												"method": "POST",
												"header": [],
												"body": {
													"mode": "urlencoded",
													"urlencoded": [
														{
															"key": "username",
															"value": "bragalotwill@",
															"type": "text"
														},
														{
															"key": "password",
															"value": "pass123",
															"type": "text"
														},
														{
															"key": "displayName",
															"value": "wila braga1",
															"type": "text"
														},
														{
															"key": "email",
															"value": "braga1@gmail.com",
															"type": "text"
														}
													]
												},
												"url": {
													"raw": "http://localhost:5000/api/users/register",
													"protocol": "http",
													"host": [
														"localhost"
													],
													"port": "5000",
													"path": [
														"api",
														"users",
														"register"
													],
													"query": [
														{
															"key": "username",
															"value": "bragalotwill",
															"disabled": true
														}
													]
												}
											},
											"_postman_previewlanguage": null,
											"header": null,
											"cookie": [],
											"body": null
										}
									]
								},
								{
									"name": "testDisplayName",
									"request": {
										"auth": {
											"type": "bearer"
										},
										"method": "POST",
										"header": [],
										"body": {
											"mode": "urlencoded",
											"urlencoded": [
												{
													"key": "username",
													"value": "bragalotwill1",
													"type": "text"
												},
												{
													"key": "password",
													"value": "pass123",
													"type": "text"
												},
												{
													"key": "displayName",
													"value": "wila braga",
													"type": "text"
												},
												{
													"key": "email",
													"value": "braga1@gmail.com",
													"type": "text"
												}
											]
										},
										"url": {
											"raw": "http://localhost:5000/api/users/register",
											"protocol": "http",
											"host": [
												"localhost"
											],
											"port": "5000",
											"path": [
												"api",
												"users",
												"register"
											]
										}
									},
									"response": [
										{
											"name": "testDisplayNameTooSmall",
											"originalRequest": {
												"method": "POST",
												"header": [],
												"body": {
													"mode": "urlencoded",
													"urlencoded": [
														{
															"key": "username",
															"value": "bragalotwill1",
															"type": "text"
														},
														{
															"key": "password",
															"value": "pass123",
															"type": "text"
														},
														{
															"key": "displayName",
															"value": "wi",
															"type": "text"
														},
														{
															"key": "email",
															"value": "braga1@gmail.com",
															"type": "text"
														}
													]
												},
												"url": {
													"raw": "http://localhost:5000/api/users/register",
													"protocol": "http",
													"host": [
														"localhost"
													],
													"port": "5000",
													"path": [
														"api",
														"users",
														"register"
													],
													"query": [
														{
															"key": "username",
															"value": "bragalotwill",
															"disabled": true
														}
													]
												}
											},
											"_postman_previewlanguage": null,
											"header": null,
											"cookie": [],
											"body": null
										},
										{
											"name": "testDisplayNameTooBig",
											"originalRequest": {
												"method": "POST",
												"header": [],
												"body": {
													"mode": "urlencoded",
													"urlencoded": [
														{
															"key": "username",
															"value": "bragalotwill",
															"type": "text"
														},
														{
															"key": "password",
															"value": "pass123",
															"type": "text"
														},
														{
															"key": "displayName",
															"value": "wila bragaa adfpjapodfj 2340 23",
															"type": "text"
														},
														{
															"key": "email",
															"value": "braga@gmail.com",
															"type": "text"
														}
													]
												},
												"url": {
													"raw": "http://localhost:5000/api/users/register",
													"protocol": "http",
													"host": [
														"localhost"
													],
													"port": "5000",
													"path": [
														"api",
														"users",
														"register"
													],
													"query": [
														{
															"key": "username",
															"value": "bragalotwill",
															"disabled": true
														}
													]
												}
											},
											"_postman_previewlanguage": null,
											"header": null,
											"cookie": [],
											"body": null
										},
										{
											"name": "testDisplayNameInvalid",
											"originalRequest": {
												"method": "POST",
												"header": [],
												"body": {
													"mode": "urlencoded",
													"urlencoded": [
														{
															"key": "username",
															"value": "bragalotwill1",
															"type": "text"
														},
														{
															"key": "password",
															"value": "pass123",
															"type": "text"
														},
														{
															"key": "displayName",
															"value": "wila - braga",
															"type": "text"
														},
														{
															"key": "email",
															"value": "braga1@gmail.com",
															"type": "text"
														}
													]
												},
												"url": {
													"raw": "http://localhost:5000/api/users/register",
													"protocol": "http",
													"host": [
														"localhost"
													],
													"port": "5000",
													"path": [
														"api",
														"users",
														"register"
													],
													"query": [
														{
															"key": "username",
															"value": "bragalotwill",
															"disabled": true
														}
													]
												}
											},
											"_postman_previewlanguage": null,
											"header": null,
											"cookie": [],
											"body": null
										}
									]
								},
								{
									"name": "testEmail",
									"request": {
										"auth": {
											"type": "bearer"
										},
										"method": "POST",
										"header": [],
										"body": {
											"mode": "urlencoded",
											"urlencoded": [
												{
													"key": "username",
													"value": "bragalotwill1",
													"type": "text"
												},
												{
													"key": "password",
													"value": "pass123",
													"type": "text"
												},
												{
													"key": "displayName",
													"value": "wila braga",
													"type": "text"
												},
												{
													"key": "email",
													"value": "braga@gmail.com",
													"type": "text"
												}
											]
										},
										"url": {
											"raw": "http://localhost:5000/api/users/register",
											"protocol": "http",
											"host": [
												"localhost"
											],
											"port": "5000",
											"path": [
												"api",
												"users",
												"register"
											],
											"query": [
												{
													"key": "username",
													"value": "bragalotwill",
													"disabled": true
												}
											]
										}
									},
									"response": [
										{
											"name": "testEmailExists",
											"originalRequest": {
												"method": "POST",
												"header": [],
												"body": {
													"mode": "urlencoded",
													"urlencoded": [
														{
															"key": "username",
															"value": "bragalotwill1",
															"type": "text"
														},
														{
															"key": "password",
															"value": "pass123",
															"type": "text"
														},
														{
															"key": "displayName",
															"value": "wila braga",
															"type": "text"
														},
														{
															"key": "email",
															"value": "braga@gmail.com",
															"type": "text"
														}
													]
												},
												"url": {
													"raw": "http://localhost:5000/api/users/register",
													"protocol": "http",
													"host": [
														"localhost"
													],
													"port": "5000",
													"path": [
														"api",
														"users",
														"register"
													],
													"query": [
														{
															"key": "username",
															"value": "bragalotwill",
															"disabled": true
														}
													]
												}
											},
											"_postman_previewlanguage": null,
											"header": null,
											"cookie": [],
											"body": null
										},
										{
											"name": "testEmailInvalid",
											"originalRequest": {
												"method": "POST",
												"header": [],
												"body": {
													"mode": "urlencoded",
													"urlencoded": [
														{
															"key": "username",
															"value": "bragalotwill1",
															"type": "text"
														},
														{
															"key": "password",
															"value": "pass123",
															"type": "text"
														},
														{
															"key": "displayName",
															"value": "wila braga",
															"type": "text"
														},
														{
															"key": "email",
															"value": "br@g",
															"type": "text"
														}
													]
												},
												"url": {
													"raw": "http://localhost:5000/api/users/register",
													"protocol": "http",
													"host": [
														"localhost"
													],
													"port": "5000",
													"path": [
														"api",
														"users",
														"register"
													],
													"query": [
														{
															"key": "username",
															"value": "bragalotwill",
															"disabled": true
														}
													]
												}
											},
											"_postman_previewlanguage": null,
											"header": null,
											"cookie": [],
											"body": null
										}
									]
								},
								{
									"name": "testPassword",
									"request": {
										"auth": {
											"type": "bearer"
										},
										"method": "POST",
										"header": [],
										"body": {
											"mode": "urlencoded",
											"urlencoded": [
												{
													"key": "username",
													"value": "bragalotwill",
													"type": "text"
												},
												{
													"key": "password",
													"value": "pass123",
													"type": "text"
												},
												{
													"key": "displayName",
													"value": "wila braga",
													"type": "text"
												},
												{
													"key": "email",
													"value": "braga@gmail.com",
													"type": "text"
												}
											]
										},
										"url": {
											"raw": "http://localhost:5000/api/users/register",
											"protocol": "http",
											"host": [
												"localhost"
											],
											"port": "5000",
											"path": [
												"api",
												"users",
												"register"
											],
											"query": [
												{
													"key": "username",
													"value": "bragalotwill",
													"disabled": true
												}
											]
										}
									},
									"response": [
										{
											"name": "testPasswordInvalid",
											"originalRequest": {
												"method": "POST",
												"header": [],
												"body": {
													"mode": "urlencoded",
													"urlencoded": [
														{
															"key": "username",
															"value": "bragalotwill",
															"type": "text"
														},
														{
															"key": "password",
															"value": "pass1232++/\\<>",
															"type": "text"
														},
														{
															"key": "displayName",
															"value": "wila braga",
															"type": "text"
														},
														{
															"key": "email",
															"value": "braga@gmail.com",
															"type": "text"
														}
													]
												},
												"url": {
													"raw": "http://localhost:5000/api/users/register",
													"protocol": "http",
													"host": [
														"localhost"
													],
													"port": "5000",
													"path": [
														"api",
														"users",
														"register"
													],
													"query": [
														{
															"key": "username",
															"value": "bragalotwill",
															"disabled": true
														}
													]
												}
											},
											"_postman_previewlanguage": null,
											"header": null,
											"cookie": [],
											"body": null
										}
									]
								},
								{
									"name": "testPfp",
									"request": {
										"auth": {
											"type": "bearer"
										},
										"method": "POST",
										"header": [],
										"body": {
											"mode": "urlencoded",
											"urlencoded": [
												{
													"key": "username",
													"value": "bragalotwill",
													"type": "text"
												},
												{
													"key": "password",
													"value": "pass123",
													"type": "text"
												},
												{
													"key": "displayName",
													"value": "wila braga",
													"type": "text"
												},
												{
													"key": "email",
													"value": "braga@gmail.com",
													"type": "text"
												}
											]
										},
										"url": {
											"raw": "http://localhost:5000/api/users/register",
											"protocol": "http",
											"host": [
												"localhost"
											],
											"port": "5000",
											"path": [
												"api",
												"users",
												"register"
											],
											"query": [
												{
													"key": "username",
													"value": "bragalotwill",
													"disabled": true
												}
											]
										}
									},
									"response": [
										{
											"name": "testPfpInvalid",
											"originalRequest": {
												"method": "POST",
												"header": [],
												"body": {
													"mode": "urlencoded",
													"urlencoded": [
														{
															"key": "username",
															"value": "bragalotwill1",
															"type": "text"
														},
														{
															"key": "password",
															"value": "pass123",
															"type": "text"
														},
														{
															"key": "displayName",
															"value": "wila braga",
															"type": "text"
														},
														{
															"key": "email",
															"value": "braga1@gmail.com",
															"type": "text"
														},
														{
															"key": "pfp",
															"value": "",
															"type": "text"
														}
													]
												},
												"url": {
													"raw": "http://localhost:5000/api/users/register",
													"protocol": "http",
													"host": [
														"localhost"
													],
													"port": "5000",
													"path": [
														"api",
														"users",
														"register"
													],
													"query": [
														{
															"key": "username",
															"value": "bragalotwill",
															"disabled": true
														}
													]
												}
											},
											"_postman_previewlanguage": null,
											"header": null,
											"cookie": [],
											"body": null
										}
									]
								}
							]
						},
						{
							"name": "bragalotwill",
							"request": {
								"auth": {
									"type": "bearer"
								},
								"method": "POST",
								"header": [],
								"body": {
									"mode": "urlencoded",
									"urlencoded": [
										{
											"key": "username",
											"value": "bragalotwill",
											"type": "text"
										},
										{
											"key": "password",
											"value": "pass123",
											"type": "text"
										},
										{
											"key": "displayName",
											"value": "wila braga",
											"type": "text"
										},
										{
											"key": "email",
											"value": "braga@gmail.com",
											"type": "text"
										}
									]
								},
								"url": {
									"raw": "http://localhost:5000/api/users/register",
									"protocol": "http",
									"host": [
										"localhost"
									],
									"port": "5000",
									"path": [
										"api",
										"users",
										"register"
									],
									"query": [
										{
											"key": "username",
											"value": "bragalotwill",
											"disabled": true
										}
									]
								}
							},
							"response": []
						},
						{
							"name": "noPenny",
							"request": {
								"auth": {
									"type": "bearer"
								},
								"method": "POST",
								"header": [],
								"body": {
									"mode": "urlencoded",
									"urlencoded": [
										{
											"key": "username",
											"value": "noPenny",
											"type": "text"
										},
										{
											"key": "password",
											"value": "pass123",
											"type": "text"
										},
										{
											"key": "displayName",
											"value": "no pennies",
											"type": "text"
										},
										{
											"key": "email",
											"value": "123@gmail.com",
											"type": "text"
										}
									]
								},
								"url": {
									"raw": "http://localhost:5000/api/users/register",
									"protocol": "http",
									"host": [
										"localhost"
									],
									"port": "5000",
									"path": [
										"api",
										"users",
										"register"
									]
								}
							},
							"response": []
						},
						{
							"name": "highRoller",
							"request": {
								"auth": {
									"type": "bearer"
								},
								"method": "POST",
								"header": [],
								"body": {
									"mode": "urlencoded",
									"urlencoded": [
										{
											"key": "username",
											"value": "bragalotwill",
											"type": "text"
										},
										{
											"key": "password",
											"value": "pass123",
											"type": "text"
										},
										{
											"key": "displayName",
											"value": "wila braga",
											"type": "text"
										},
										{
											"key": "email",
											"value": "braga@gmail.com",
											"type": "text"
										}
									]
								},
								"url": {
									"raw": "http://localhost:5000/api/users/register",
									"protocol": "http",
									"host": [
										"localhost"
									],
									"port": "5000",
									"path": [
										"api",
										"users",
										"register"
									],
									"query": [
										{
											"key": "username",
											"value": "bragalotwill",
											"disabled": true
										}
									]
								}
							},
							"response": []
						}
					]
				},
				{
					"name": "Login",
					"item": [
						{
							"name": "Error",
							"item": [
								{
									"name": "testUsername",
									"request": {
										"method": "POST",
										"header": [],
										"body": {
											"mode": "urlencoded",
											"urlencoded": [
												{
													"key": "username",
													"value": "bragalotwill",
													"type": "text"
												},
												{
													"key": "password",
													"value": "pass123",
													"type": "text"
												}
											]
										},
										"url": {
											"raw": "http://localhost:5000/api/users/login",
											"protocol": "http",
											"host": [
												"localhost"
											],
											"port": "5000",
											"path": [
												"api",
												"users",
												"login"
											]
										}
									},
									"response": [
										{
											"name": "testUsernameInvalid",
											"originalRequest": {
												"method": "POST",
												"header": [],
												"body": {
													"mode": "urlencoded",
													"urlencoded": [
														{
															"key": "username",
															"value": "bragalotwill<script>",
															"type": "text"
														},
														{
															"key": "password",
															"value": "pass123",
															"type": "text"
														}
													]
												},
												"url": {
													"raw": "http://localhost:5000/api/users/login",
													"protocol": "http",
													"host": [
														"localhost"
													],
													"port": "5000",
													"path": [
														"api",
														"users",
														"login"
													]
												}
											},
											"_postman_previewlanguage": null,
											"header": null,
											"cookie": [],
											"body": null
										},
										{
											"name": "testUsernameDNE",
											"originalRequest": {
												"method": "POST",
												"header": [],
												"body": {
													"mode": "urlencoded",
													"urlencoded": [
														{
															"key": "username",
															"value": "bragalotwill",
															"type": "text"
														},
														{
															"key": "password",
															"value": "pass123",
															"type": "text"
														}
													]
												},
												"url": {
													"raw": "http://localhost:5000/api/users/login",
													"protocol": "http",
													"host": [
														"localhost"
													],
													"port": "5000",
													"path": [
														"api",
														"users",
														"login"
													]
												}
											},
											"_postman_previewlanguage": null,
											"header": null,
											"cookie": [],
											"body": null
										}
									]
								},
								{
									"name": "testPassword",
									"request": {
										"method": "POST",
										"header": [],
										"body": {
											"mode": "urlencoded",
											"urlencoded": [
												{
													"key": "username",
													"value": "bragalotwill",
													"type": "text"
												},
												{
													"key": "password",
													"value": "pass123",
													"type": "text"
												}
											]
										},
										"url": {
											"raw": "http://localhost:5000/api/users/login",
											"protocol": "http",
											"host": [
												"localhost"
											],
											"port": "5000",
											"path": [
												"api",
												"users",
												"login"
											]
										}
									},
									"response": [
										{
											"name": "testPasswordInvalid",
											"originalRequest": {
												"method": "POST",
												"header": [],
												"body": {
													"mode": "urlencoded",
													"urlencoded": [
														{
															"key": "username",
															"value": "bragalotwill",
															"type": "text"
														},
														{
															"key": "password",
															"value": "pass123<script>",
															"type": "text"
														}
													]
												},
												"url": {
													"raw": "http://localhost:5000/api/users/login",
													"protocol": "http",
													"host": [
														"localhost"
													],
													"port": "5000",
													"path": [
														"api",
														"users",
														"login"
													]
												}
											},
											"_postman_previewlanguage": null,
											"header": null,
											"cookie": [],
											"body": null
										},
										{
											"name": "testPasswordIncorrect",
											"originalRequest": {
												"method": "POST",
												"header": [],
												"body": {
													"mode": "urlencoded",
													"urlencoded": [
														{
															"key": "username",
															"value": "bragalotwill",
															"type": "text"
														},
														{
															"key": "password",
															"value": "pass12",
															"type": "text"
														}
													]
												},
												"url": {
													"raw": "http://localhost:5000/api/users/login",
													"protocol": "http",
													"host": [
														"localhost"
													],
													"port": "5000",
													"path": [
														"api",
														"users",
														"login"
													]
												}
											},
											"_postman_previewlanguage": null,
											"header": null,
											"cookie": [],
											"body": null
										}
									]
								}
							]
						},
						{
							"name": "bragalotwill",
							"request": {
								"method": "POST",
								"header": [],
								"body": {
									"mode": "urlencoded",
									"urlencoded": [
										{
											"key": "username",
											"value": "bragalotwill",
											"type": "text"
										},
										{
											"key": "password",
											"value": "pass123",
											"type": "text"
										}
									]
								},
								"url": {
									"raw": "http://localhost:5000/api/users/login",
									"protocol": "http",
									"host": [
										"localhost"
									],
									"port": "5000",
									"path": [
										"api",
										"users",
										"login"
									]
								}
							},
							"response": []
						},
						{
							"name": "highRoller",
							"request": {
								"method": "POST",
								"header": [],
								"body": {
									"mode": "urlencoded",
									"urlencoded": [
										{
											"key": "username",
											"value": "highRoller",
											"type": "text"
										},
										{
											"key": "password",
											"value": "pass123",
											"type": "text"
										}
									]
								},
								"url": {
									"raw": "http://localhost:5000/api/users/login",
									"protocol": "http",
									"host": [
										"localhost"
									],
									"port": "5000",
									"path": [
										"api",
										"users",
										"login"
									]
								}
							},
							"response": []
						}
					]
				},
				{
					"name": "Get",
					"item": [
						{
							"name": "Error",
							"item": [
								{
									"name": "testGetMeNoToken",
									"request": {
										"method": "GET",
										"header": [],
										"url": {
											"raw": "http://localhost:5000/api/users/",
											"protocol": "http",
											"host": [
												"localhost"
											],
											"port": "5000",
											"path": [
												"api",
												"users",
												""
											]
										}
									},
									"response": []
								},
								{
									"name": "testGetMeWrongToken",
									"request": {
										"auth": {
											"type": "bearer",
											"bearer": [
												{
													"key": "token",
													"value": "JhbGciOiJIUzI1NiIsInR5cCI6IkpXVCJ9.eyJfaWQiOiI2NDU5YTEwMjQzMGIwNGVlMjk4MzQwMGQiLCJpYXQiOjE2ODM1OTcxNzQsImV4cCI6MTY4MzY4MzU3NH0.U5nQKP3l6aC4ONT1R2wx04hzdVYbq_WfSKjZzYqw2Y0",
													"type": "string"
												}
											]
										},
										"method": "GET",
										"header": [],
										"url": {
											"raw": "http://localhost:5000/api/users/",
											"protocol": "http",
											"host": [
												"localhost"
											],
											"port": "5000",
											"path": [
												"api",
												"users",
												""
											]
										}
									},
									"response": []
								},
								{
									"name": "testGetMeOldToken",
									"request": {
										"method": "GET",
										"header": [],
										"url": {
											"raw": "http://localhost:5000/api/users/",
											"protocol": "http",
											"host": [
												"localhost"
											],
											"port": "5000",
											"path": [
												"api",
												"users",
												""
											]
										}
									},
									"response": []
								}
							]
						},
						{
							"name": "getMe",
							"protocolProfileBehavior": {
								"disableBodyPruning": true
							},
							"request": {
								"auth": {
									"type": "bearer",
									"bearer": [
										{
											"key": "token",
											"value": "eyJhbGciOiJIUzI1NiIsInR5cCI6IkpXVCJ9.eyJfaWQiOiI2NDU5YTEwMjQzMGIwNGVlMjk4MzQwMGQiLCJpYXQiOjE2ODM3Njk4NDEsImV4cCI6MTY4Mzg1NjI0MX0.lDXPYLUhEMx0YT6-fqYPZO8tJkeQCaqc4pFNV7wOluc",
											"type": "string"
										}
									]
								},
								"method": "GET",
								"header": [],
								"body": {
									"mode": "urlencoded",
									"urlencoded": []
								},
								"url": {
									"raw": "http://localhost:5000/api/users/",
									"protocol": "http",
									"host": [
										"localhost"
									],
									"port": "5000",
									"path": [
										"api",
										"users",
										""
									]
								}
							},
							"response": []
						}
					]
				},
				{
					"name": "Pennies",
					"item": [
						{
							"name": "Error",
							"item": [
								{
									"name": "testAddPenniesInvalidPennies",
									"request": {
										"auth": {
											"type": "bearer",
											"bearer": [
												{
													"key": "token",
													"value": "eyJhbGciOiJIUzI1NiIsInR5cCI6IkpXVCJ9.eyJfaWQiOiI2NDU5YTEwMjQzMGIwNGVlMjk4MzQwMGQiLCJpYXQiOjE2ODM1OTcxNzQsImV4cCI6MTY4MzY4MzU3NH0.U5nQKP3l6aC4ONT1R2wx04hzdVYbq_WfSKjZzYqw2Y0",
													"type": "string"
												}
											]
										},
										"method": "POST",
										"header": [],
										"body": {
											"mode": "urlencoded",
											"urlencoded": [
												{
													"key": "penniesToAdd",
													"value": "10!",
													"type": "text"
												}
											]
										},
										"url": {
											"raw": "http://localhost:5000/api/users/pennies",
											"protocol": "http",
											"host": [
												"localhost"
											],
											"port": "5000",
											"path": [
												"api",
												"users",
												"pennies"
											]
										}
									},
									"response": []
								}
							]
						},
						{
							"name": "addPennies",
							"request": {
								"auth": {
									"type": "bearer",
									"bearer": [
										{
											"key": "token",
											"value": "eyJhbGciOiJIUzI1NiIsInR5cCI6IkpXVCJ9.eyJfaWQiOiI2NDViZGFiMGE4NTJjODI2MDQ3NTZhNDAiLCJpYXQiOjE2ODM3NDEzNjAsImV4cCI6MTY4MzgyNzc2MH0.0X8s4QyNhbItcGc3fEdv4FV0vqgFbcLwfSRfAakmyAk",
											"type": "string"
										}
									]
								},
								"method": "POST",
								"header": [],
								"body": {
									"mode": "urlencoded",
									"urlencoded": [
										{
											"key": "penniesToAdd",
											"value": "100000",
											"type": "text"
										}
									]
								},
								"url": {
									"raw": "http://localhost:5000/api/users/pennies",
									"protocol": "http",
									"host": [
										"localhost"
									],
									"port": "5000",
									"path": [
										"api",
										"users",
										"pennies"
									]
								}
							},
							"response": []
						}
					]
				}
			]
		},
		{
			"name": "Post",
			"item": [
				{
					"name": "Make",
					"item": [
						{
							"name": "Error",
							"item": [
								{
									"name": "testNoImgOrText",
									"request": {
										"auth": {
											"type": "bearer",
											"bearer": [
												{
													"key": "token",
													"value": "eyJhbGciOiJIUzI1NiIsInR5cCI6IkpXVCJ9.eyJfaWQiOiI2NDU5YTEwMjQzMGIwNGVlMjk4MzQwMGQiLCJpYXQiOjE2ODM3Mzk2NTMsImV4cCI6MTY4MzgyNjA1M30.yqnOAQeU_IZ8GRVzYfwDt6-bJd95GRLMP7rYRi47Teo",
													"type": "string"
												}
											]
										},
										"method": "POST",
										"header": [],
										"body": {
											"mode": "urlencoded",
											"urlencoded": [
												{
													"key": "text",
													"value": "hello world!",
													"type": "text",
													"disabled": true
												}
											]
										},
										"url": {
											"raw": "http://localhost:5000/api/posts/create",
											"protocol": "http",
											"host": [
												"localhost"
											],
											"port": "5000",
											"path": [
												"api",
												"posts",
												"create"
											]
										}
									},
									"response": []
								},
								{
									"name": "testInvalidText",
									"request": {
										"auth": {
											"type": "bearer",
											"bearer": [
												{
													"key": "token",
													"value": "eyJhbGciOiJIUzI1NiIsInR5cCI6IkpXVCJ9.eyJfaWQiOiI2NDU5YTEwMjQzMGIwNGVlMjk4MzQwMGQiLCJpYXQiOjE2ODM3Mzk2NTMsImV4cCI6MTY4MzgyNjA1M30.yqnOAQeU_IZ8GRVzYfwDt6-bJd95GRLMP7rYRi47Teo",
													"type": "string"
												}
											]
										},
										"method": "POST",
										"header": [],
										"body": {
											"mode": "urlencoded",
											"urlencoded": [
												{
													"key": "text",
													"value": "hello world! <script>",
													"type": "text"
												}
											]
										},
										"url": {
											"raw": "http://localhost:5000/api/posts/create",
											"protocol": "http",
											"host": [
												"localhost"
											],
											"port": "5000",
											"path": [
												"api",
												"posts",
												"create"
											]
										}
									},
									"response": []
								},
								{
									"name": "testInvalidImage",
									"request": {
										"method": "POST",
										"header": [],
										"body": {
											"mode": "urlencoded",
											"urlencoded": [
												{
													"key": "text",
													"value": "hello world!",
													"type": "text"
												}
											]
										},
										"url": {
											"raw": "http://localhost:5000/api/posts/create",
											"protocol": "http",
											"host": [
												"localhost"
											],
											"port": "5000",
											"path": [
												"api",
												"posts",
												"create"
											]
										}
									},
									"response": []
								},
								{
									"name": "testNoPennies",
									"request": {
										"auth": {
											"type": "bearer",
											"bearer": [
												{
													"key": "token",
													"value": "eyJhbGciOiJIUzI1NiIsInR5cCI6IkpXVCJ9.eyJfaWQiOiI2NDViZDYwMjg2NjMyNWM1ZmQ5YjlkOTkiLCJpYXQiOjE2ODM3NDAxNjIsImV4cCI6MTY4MzgyNjU2Mn0.QHFEuwHpC2ZW_6PdMhEW25tcX5F2WU3Hwo0ipOo-Qxw",
													"type": "string"
												}
											]
										},
										"method": "POST",
										"header": [],
										"body": {
											"mode": "urlencoded",
											"urlencoded": [
												{
													"key": "text",
													"value": "hello world!",
													"type": "text"
												}
											]
										},
										"url": {
											"raw": "http://localhost:5000/api/posts/create",
											"protocol": "http",
											"host": [
												"localhost"
											],
											"port": "5000",
											"path": [
												"api",
												"posts",
												"create"
											]
										}
									},
									"response": []
								}
							]
						},
						{
							"name": "makePostText",
							"request": {
								"auth": {
									"type": "bearer",
									"bearer": [
										{
											"key": "token",
											"value": "eyJhbGciOiJIUzI1NiIsInR5cCI6IkpXVCJ9.eyJfaWQiOiI2NDU5YTEwMjQzMGIwNGVlMjk4MzQwMGQiLCJpYXQiOjE2ODM3Mzk2NTMsImV4cCI6MTY4MzgyNjA1M30.yqnOAQeU_IZ8GRVzYfwDt6-bJd95GRLMP7rYRi47Teo",
											"type": "string"
										}
									]
								},
								"method": "POST",
								"header": [],
								"body": {
									"mode": "urlencoded",
									"urlencoded": [
										{
											"key": "text",
											"value": "hello world!2",
											"type": "text"
										}
									]
								},
								"url": {
									"raw": "http://localhost:5000/api/posts/create",
									"protocol": "http",
									"host": [
										"localhost"
									],
									"port": "5000",
									"path": [
										"api",
										"posts",
										"create"
									]
								}
							},
							"response": []
						},
						{
							"name": "makePostTextImage",
							"request": {
								"auth": {
									"type": "bearer",
									"bearer": [
										{
											"key": "token",
											"value": "eyJhbGciOiJIUzI1NiIsInR5cCI6IkpXVCJ9.eyJfaWQiOiI2NDU5YTEwMjQzMGIwNGVlMjk4MzQwMGQiLCJpYXQiOjE2ODM3Mzk2NTMsImV4cCI6MTY4MzgyNjA1M30.yqnOAQeU_IZ8GRVzYfwDt6-bJd95GRLMP7rYRi47Teo",
											"type": "string"
										}
									]
								},
								"method": "POST",
								"header": [],
								"body": {
									"mode": "urlencoded",
									"urlencoded": [
										{
											"key": "text",
											"value": "hello world!",
											"type": "text"
										},
										{
											"key": "image",
											"value": "/image/asset.png",
											"type": "text"
										}
									]
								},
								"url": {
									"raw": "http://localhost:5000/api/posts/create",
									"protocol": "http",
									"host": [
										"localhost"
									],
									"port": "5000",
									"path": [
										"api",
										"posts",
										"create"
									]
								}
							},
							"response": []
						},
						{
							"name": "makePostImage",
							"request": {
								"auth": {
									"type": "bearer",
									"bearer": [
										{
											"key": "token",
											"value": "eyJhbGciOiJIUzI1NiIsInR5cCI6IkpXVCJ9.eyJfaWQiOiI2NDU5YTEwMjQzMGIwNGVlMjk4MzQwMGQiLCJpYXQiOjE2ODM3Mzk2NTMsImV4cCI6MTY4MzgyNjA1M30.yqnOAQeU_IZ8GRVzYfwDt6-bJd95GRLMP7rYRi47Teo",
											"type": "string"
										}
									]
								},
								"method": "POST",
								"header": [],
								"body": {
									"mode": "urlencoded",
									"urlencoded": [
										{
											"key": "text",
											"value": "hello world!",
											"type": "text",
											"disabled": true
										},
										{
											"key": "image",
											"value": "assets/image.png",
											"type": "text"
										}
									]
								},
								"url": {
									"raw": "http://localhost:5000/api/posts/create",
									"protocol": "http",
									"host": [
										"localhost"
									],
									"port": "5000",
									"path": [
										"api",
										"posts",
										"create"
									]
								}
							},
							"response": []
						}
					]
				},
				{
					"name": "Like",
					"item": [
						{
							"name": "Error",
							"item": [
								{
									"name": "testUser",
									"request": {
										"method": "POST",
										"header": [],
										"body": {
											"mode": "urlencoded",
											"urlencoded": [
												{
													"key": "_id",
													"value": "645988a89456e9ca3b7022e0",
													"type": "text"
												}
											]
										},
										"url": {
											"raw": "http://localhost:5000/api/posts/like",
											"protocol": "http",
											"host": [
												"localhost"
											],
											"port": "5000",
											"path": [
												"api",
												"posts",
												"like"
											]
										}
									},
									"response": [
										{
											"name": "testUserIsCreator",
											"originalRequest": {
												"method": "POST",
												"header": [],
												"body": {
													"mode": "urlencoded",
													"urlencoded": [
														{
															"key": "_id",
															"value": "645988a89456e9ca3b7022e0",
															"type": "text"
														}
													]
												},
												"url": {
													"raw": "http://localhost:5000/api/posts/like",
													"protocol": "http",
													"host": [
														"localhost"
													],
													"port": "5000",
													"path": [
														"api",
														"posts",
														"like"
													]
												}
											},
											"_postman_previewlanguage": null,
											"header": null,
											"cookie": [],
											"body": null
										},
										{
											"name": "testUserRelikes",
											"originalRequest": {
												"method": "POST",
												"header": [],
												"body": {
													"mode": "urlencoded",
													"urlencoded": [
														{
															"key": "_id",
															"value": "645988a89456e9ca3b7022e0",
															"type": "text"
														}
													]
												},
												"url": {
													"raw": "http://localhost:5000/api/posts/like",
													"protocol": "http",
													"host": [
														"localhost"
													],
													"port": "5000",
													"path": [
														"api",
														"posts",
														"like"
													]
												}
											},
											"_postman_previewlanguage": null,
											"header": null,
											"cookie": [],
											"body": null
										},
										{
											"name": "testUserNoPennies",
											"originalRequest": {
												"method": "POST",
												"header": [],
												"body": {
													"mode": "urlencoded",
													"urlencoded": [
														{
															"key": "_id",
															"value": "645988a89456e9ca3b7022e0",
															"type": "text"
														}
													]
												},
												"url": {
													"raw": "http://localhost:5000/api/posts/like",
													"protocol": "http",
													"host": [
														"localhost"
													],
													"port": "5000",
													"path": [
														"api",
														"posts",
														"like"
													]
												}
											},
											"_postman_previewlanguage": null,
											"header": null,
											"cookie": [],
											"body": null
										}
									]
								},
								{
									"name": "testPost",
									"request": {
										"method": "POST",
										"header": [],
										"body": {
											"mode": "urlencoded",
											"urlencoded": [
												{
													"key": "_id",
													"value": "645988a89456e9ca3b7022e0",
													"type": "text"
												}
											]
										},
										"url": {
											"raw": "http://localhost:5000/api/posts/like",
											"protocol": "http",
											"host": [
												"localhost"
											],
											"port": "5000",
											"path": [
												"api",
												"posts",
												"like"
											]
										}
									},
									"response": [
										{
											"name": "testInvalidId",
											"originalRequest": {
												"method": "POST",
												"header": [],
												"body": {
													"mode": "urlencoded",
													"urlencoded": [
														{
															"key": "_id",
															"value": "645988a89456e9ca3b7022e0",
															"type": "text"
														}
													]
												},
												"url": {
													"raw": "http://localhost:5000/api/posts/like",
													"protocol": "http",
													"host": [
														"localhost"
													],
													"port": "5000",
													"path": [
														"api",
														"posts",
														"like"
													]
												}
											},
											"_postman_previewlanguage": null,
											"header": null,
											"cookie": [],
											"body": null
										},
										{
											"name": "testPostNotFound",
											"originalRequest": {
												"method": "POST",
												"header": [],
												"body": {
													"mode": "urlencoded",
													"urlencoded": [
														{
															"key": "_id",
															"value": "645988a89456e9ca3b7022e0",
															"type": "text"
														}
													]
												},
												"url": {
													"raw": "http://localhost:5000/api/posts/like",
													"protocol": "http",
													"host": [
														"localhost"
													],
													"port": "5000",
													"path": [
														"api",
														"posts",
														"like"
													]
												}
											},
											"_postman_previewlanguage": null,
											"header": null,
											"cookie": [],
											"body": null
										}
									]
								}
							]
						},
						{
							"name": "likePost",
							"request": {
								"auth": {
									"type": "bearer",
									"bearer": [
										{
											"key": "token",
											"value": "eyJhbGciOiJIUzI1NiIsInR5cCI6IkpXVCJ9.eyJfaWQiOiI2NDViZGFiMGE4NTJjODI2MDQ3NTZhNDAiLCJpYXQiOjE2ODM3Njk1NjMsImV4cCI6MTY4Mzg1NTk2M30.4UJ6kF9ait3f6WZRUV3OsWPV8Ere4i-PJeQWoHQX7Ak",
											"type": "string"
										}
									]
								},
								"method": "POST",
								"header": [],
								"body": {
									"mode": "urlencoded",
									"urlencoded": [
										{
											"key": "_id",
											"value": "645bd4c4866325c5fd9b9d91",
											"type": "text"
										}
									]
								},
								"url": {
									"raw": "http://localhost:5000/api/posts/like",
									"protocol": "http",
									"host": [
										"localhost"
									],
									"port": "5000",
									"path": [
										"api",
										"posts",
										"like"
									]
								}
							},
							"response": []
						}
					]
				},
				{
					"name": "Get",
					"item": [
						{
							"name": "Error",
							"item": [
								{
									"name": "testId",
									"protocolProfileBehavior": {
										"disableBodyPruning": true
									},
									"request": {
										"method": "GET",
										"header": [],
										"body": {
											"mode": "urlencoded",
											"urlencoded": [
												{
													"key": "_id",
													"value": "645988a89456e9ca3b7022e0",
													"type": "text"
												}
											]
										},
										"url": {
											"raw": "http://localhost:5000/api/posts/",
											"protocol": "http",
											"host": [
												"localhost"
											],
											"port": "5000",
											"path": [
												"api",
												"posts",
												""
											]
										}
									},
									"response": [
										{
											"name": "testIdDNE",
											"originalRequest": {
												"method": "GET",
												"header": [],
												"body": {
													"mode": "urlencoded",
													"urlencoded": [
														{
															"key": "id",
															"value": "645bd4af866325c5fd9b9d8a",
															"type": "text"
														}
													]
												},
												"url": {
													"raw": "http://localhost:5000/api/posts/",
													"protocol": "http",
													"host": [
														"localhost"
													],
													"port": "5000",
													"path": [
														"api",
														"posts",
														""
													]
												}
											},
											"_postman_previewlanguage": null,
											"header": null,
											"cookie": [],
											"body": null
										},
										{
											"name": "testIdInvalid",
											"originalRequest": {
												"method": "GET",
												"header": [],
												"body": {
													"mode": "urlencoded",
													"urlencoded": [
														{
															"key": "_id",
															"value": "645988a89456e9ca3b7022e0",
															"type": "text"
														}
													]
												},
												"url": {
													"raw": "http://localhost:5000/api/posts/",
													"protocol": "http",
													"host": [
														"localhost"
													],
													"port": "5000",
													"path": [
														"api",
														"posts",
														""
													]
												}
											},
											"_postman_previewlanguage": null,
											"header": null,
											"cookie": [],
											"body": null
										}
									]
								}
							]
						},
						{
							"name": "getPost",
							"protocolProfileBehavior": {
								"disableBodyPruning": true
							},
							"request": {
								"method": "GET",
								"header": [],
								"body": {
									"mode": "urlencoded",
									"urlencoded": [
										{
											"key": "id",
											"value": "645bd4af866325c5fd9b9d8d",
											"type": "text"
										}
									]
								},
								"url": {
									"raw": "http://localhost:5000/api/posts/",
									"protocol": "http",
									"host": [
										"localhost"
									],
									"port": "5000",
									"path": [
										"api",
										"posts",
										""
									]
								}
							},
							"response": []
						}
					]
				}
			]
		},
		{
			"name": "Comment",
			"item": [
				{
					"name": "Get",
					"item": [
						{
							"name": "Error",
							"item": [
								{
									"name": "testId",
									"protocolProfileBehavior": {
										"disableBodyPruning": true
									},
									"request": {
										"auth": {
											"type": "bearer",
											"bearer": [
												{
													"key": "token",
													"value": "eyJhbGciOiJIUzI1NiIsInR5cCI6IkpXVCJ9.eyJfaWQiOiI2NDU5YTEwMjQzMGIwNGVlMjk4MzQwMGQiLCJpYXQiOjE2ODM3Njk4NDEsImV4cCI6MTY4Mzg1NjI0MX0.lDXPYLUhEMx0YT6-fqYPZO8tJkeQCaqc4pFNV7wOluc",
													"type": "string"
												}
											]
										},
										"method": "GET",
										"header": [],
										"body": {
											"mode": "urlencoded",
											"urlencoded": [
												{
													"key": "_id",
													"value": "645c47729729add37e59e803",
													"type": "text"
												}
											]
										},
										"url": {
											"raw": "http://localhost:5000/api/comments",
											"protocol": "http",
											"host": [
												"localhost"
											],
											"port": "5000",
											"path": [
												"api",
												"comments"
											]
										}
									},
									"response": [
										{
											"name": "testIdInvalid",
											"originalRequest": {
												"method": "GET",
												"header": [],
												"body": {
													"mode": "urlencoded",
													"urlencoded": [
														{
															"key": "id",
															"value": "645c47729729add37e59e807<scriipt>",
															"type": "text"
														}
													]
												},
												"url": {
													"raw": "http://localhost:5000/api/comments",
													"protocol": "http",
													"host": [
														"localhost"
													],
													"port": "5000",
													"path": [
														"api",
														"comments"
													]
												}
											},
											"status": "Bad Request",
											"code": 400,
											"_postman_previewlanguage": "html",
											"header": [
												{
													"key": "X-Powered-By",
													"value": "Express"
												},
												{
													"key": "Content-Type",
													"value": "text/html; charset=utf-8"
												},
												{
													"key": "Content-Length",
													"value": "19"
												},
												{
													"key": "ETag",
													"value": "W/\"13-n1+zkEZSMb+vRnFPg9uVcQHMhzo\""
												},
												{
													"key": "Date",
													"value": "Thu, 11 May 2023 02:47:48 GMT"
												},
												{
													"key": "Connection",
													"value": "keep-alive"
												},
												{
													"key": "Keep-Alive",
													"value": "timeout=5"
												}
											],
											"cookie": [],
											"body": "Invalid comment id."
										},
										{
											"name": "testIdDNE",
											"originalRequest": {
												"method": "GET",
												"header": [],
												"body": {
													"mode": "urlencoded",
													"urlencoded": [
														{
															"key": "id",
															"value": "645c47729729add37e59e807",
															"type": "text"
														}
													]
												},
												"url": {
													"raw": "http://localhost:5000/api/comments",
													"protocol": "http",
													"host": [
														"localhost"
													],
													"port": "5000",
													"path": [
														"api",
														"comments"
													]
												}
											},
											"status": "Bad Request",
											"code": 400,
											"_postman_previewlanguage": "html",
											"header": [
												{
													"key": "X-Powered-By",
													"value": "Express"
												},
												{
													"key": "Content-Type",
													"value": "text/html; charset=utf-8"
												},
												{
													"key": "Content-Length",
													"value": "19"
												},
												{
													"key": "ETag",
													"value": "W/\"13-n1+zkEZSMb+vRnFPg9uVcQHMhzo\""
												},
												{
													"key": "Date",
													"value": "Thu, 11 May 2023 02:48:00 GMT"
												},
												{
													"key": "Connection",
													"value": "keep-alive"
												},
												{
													"key": "Keep-Alive",
													"value": "timeout=5"
												}
											],
											"cookie": [],
											"body": "Invalid comment id."
										}
									]
								}
							]
						},
						{
							"name": "getComment",
							"protocolProfileBehavior": {
								"disableBodyPruning": true
							},
							"request": {
								"auth": {
									"type": "bearer",
									"bearer": [
										{
											"key": "token",
											"value": "eyJhbGciOiJIUzI1NiIsInR5cCI6IkpXVCJ9.eyJfaWQiOiI2NDU5YTEwMjQzMGIwNGVlMjk4MzQwMGQiLCJpYXQiOjE2ODM3Njk4NDEsImV4cCI6MTY4Mzg1NjI0MX0.lDXPYLUhEMx0YT6-fqYPZO8tJkeQCaqc4pFNV7wOluc",
											"type": "string"
										}
									]
								},
								"method": "GET",
								"header": [],
								"body": {
									"mode": "urlencoded",
									"urlencoded": [
										{
											"key": "id",
											"value": "645c47729729add37e59e807",
											"type": "text"
										}
									]
								},
								"url": {
									"raw": "http://localhost:5000/api/comments",
									"protocol": "http",
									"host": [
										"localhost"
									],
									"port": "5000",
									"path": [
										"api",
										"comments"
									]
								}
							},
							"response": []
						}
					]
				},
				{
					"name": "Make",
					"item": [
						{
							"name": "Error",
							"item": []
						},
						{
							"name": "makeComment",
							"request": {
								"auth": {
									"type": "bearer",
									"bearer": [
										{
											"key": "token",
											"value": "eyJhbGciOiJIUzI1NiIsInR5cCI6IkpXVCJ9.eyJfaWQiOiI2NDU5YTEwMjQzMGIwNGVlMjk4MzQwMGQiLCJpYXQiOjE2ODM3NjAyNTgsImV4cCI6MTY4Mzg0NjY1OH0.FjaHhtGVNQSWkOn1RaPurVJLoXETjQWjUHMbCDI22wM",
											"type": "string"
										}
									]
								},
								"method": "POST",
								"header": [],
								"body": {
									"mode": "urlencoded",
									"urlencoded": [
										{
											"key": "postId",
											"value": "645bd4af866325c5fd9b9d8d",
											"type": "text"
										},
										{
											"key": "parentCommentId",
											"value": "645c47729729add37e59e807",
											"type": "text"
										},
										{
											"key": "image",
											"value": "",
											"type": "text",
											"disabled": true
										},
										{
											"key": "text",
											"value": "booChild",
											"type": "text"
										}
									]
								},
								"url": {
									"raw": "http://localhost:5000/api/comments/create",
									"protocol": "http",
									"host": [
										"localhost"
									],
									"port": "5000",
									"path": [
										"api",
										"comments",
										"create"
									]
								}
							},
							"response": []
						}
					]
				},
				{
					"name": "Like",
					"item": [
						{
							"name": "Error",
							"item": []
						},
						{
							"name": "likeComment",
							"request": {
								"auth": {
									"type": "bearer",
									"bearer": [
										{
											"key": "token",
											"value": "eyJhbGciOiJIUzI1NiIsInR5cCI6IkpXVCJ9.eyJfaWQiOiI2NDViZGFiMGE4NTJjODI2MDQ3NTZhNDAiLCJpYXQiOjE2ODM3NzE1NDIsImV4cCI6MTY4Mzg1Nzk0Mn0.PK1gP4puL_e8JrEx9LapOVSYddrTFxkP-pjCPHLhi9Q",
											"type": "string"
										}
									]
								},
								"method": "POST",
								"header": [],
								"body": {
									"mode": "urlencoded",
									"urlencoded": [
										{
											"key": "id",
											"value": "645c4c31fe412de6f41d8626",
											"type": "text"
										}
									]
								},
								"url": {
									"raw": "http://localhost:5000/api/comments/like",
									"protocol": "http",
									"host": [
										"localhost"
									],
									"port": "5000",
									"path": [
										"api",
										"comments",
										"like"
									]
								}
							},
							"response": []
						}
					]
				}
			]
		}
	],
	"event": [
		{
			"listen": "prerequest",
			"script": {
				"type": "text/javascript",
				"exec": [
					""
				]
			}
		},
		{
			"listen": "test",
			"script": {
				"type": "text/javascript",
				"exec": [
					""
				]
			}
		}
	]
}